HQ_Daily_Cube/__init__.py
HQ_Daily_Cube/main.py
HQ_Daily_Cube-0.0.2.dist-info/LICENSE
HQ_Daily_Cube-0.0.2.dist-info/METADATA
HQ_Daily_Cube-0.0.2.dist-info/WHEEL
HQ_Daily_Cube-0.0.2.dist-info/top_level.txt
HQ_Daily_Cube-0.0.2.dist-info/RECORD
