Metadata-Version: 2.1
Name: HQ-Daily-Cube
Version: 0.0.2
Summary: A Python package to fetch and print Dataframe for H.Q Daily Cube.
Author-email: Hossam Ibrahim <hossam.ibrahim@hlag.com>
License: Copyright (c) [2023] [Hossam_Ibrahim]
License-File: LICENSE
Requires-Dist: requests
Requires-Dist: pandas
